Workbook

Sheet Read me
B2: SAMARKAND — terrace restaurant, Da Nang
B3: Bill of Quantities for pricing / Bảng khối lượng để báo giá — design revision R12-v8.2
C5: English | D5: Tiếng Việt
B6: Project / Dự án | C6: Tajik & Uzbek restaurant terrace: new steel roof with a glazed-tile dome, aivan platform, themed booths, tents, tapchan, bar, mangal grill, street facade. | D6: Sân thượng nhà hàng Tajik & Uzbek: mái thép mới với mái vòm gạch men, bục aivan, ô ngồi theo chủ đề, lều, tapchan, quầy bar, bếp nướng, mặt tiền.
B7: Size / Quy mô | C7: Terrace ≈ 317 m² + kids 17 m² + mangal 19 m² · roof ≈ 413 m² · 155 seats (+31 street bench seats) | D7: Sân ≈ 317 m² + trẻ em 17 m² + bếp nướng 19 m² · mái ≈ 413 m² · 155 chỗ ngồi (+31 chỗ ghế băng mặt đường)
B8: What we ask / Yêu cầu | C8: Please fill the YELLOW cells on sheet "BOQ": unit price in VND (supply + install), your note, and a status for every line. Totals calculate automatically on "Summary". | D8: Vui lòng điền các ô MÀU VÀNG trong sheet "BOQ": đơn giá VND (cung cấp + lắp đặt), ghi chú, và trạng thái cho từng dòng. Tổng tiền tự tính ở sheet "Summary".
B9: Status values / Trạng thái | C9: Priced = price given · Need info = you need a drawing / sample / answer · Alternative = you propose another material or method (describe in Note) · Not in scope = you do not do this item | D9: Priced = đã báo giá · Need info = cần thêm bản vẽ / mẫu / trả lời · Alternative = đề xuất vật liệu hoặc cách làm khác (ghi trong Note) · Not in scope = không làm hạng mục này
B10: Quantities / Khối lượng | C10: Taken from our CAD plan and 3D model. They are for comparison of offers — please check on site and correct in your Note if you measure differently. | D10: Lấy từ bản vẽ CAD và mô hình 3D. Dùng để so sánh báo giá — vui lòng kiểm tra tại công trình và ghi chú nếu đo khác.
B11: Images / Hình ảnh | C11: Each line has a picture from the 3D model. Sheet "Materials" shows the finishes (codes M01–M30), sheet "References" shows real photos the owner likes. | D11: Mỗi dòng có hình từ mô hình 3D. Sheet "Materials" là mẫu vật liệu hoàn thiện (mã M01–M30), sheet "References" là ảnh thực tế chủ đầu tư thích.
B12: Please check first / Kiểm tra trước | C12: Sheet "Design checks" lists 15 technical points (structure, fire, slip, gas, permits). Please read before pricing and comment. | D12: Sheet "Design checks" liệt kê 15 điểm kỹ thuật (kết cấu, PCCC, chống trơn, gas, giấy phép). Vui lòng đọc trước khi báo giá và góp ý.
B13: 3D model / Mô hình 3D | C13: https://claude.ai/artifact/7NGDiBpaXwuSr9gytuvAtm (open in a browser; buttons: roof, ceiling, facade, dimensions) | D13: https://claude.ai/artifact/7NGDiBpaXwuSr9gytuvAtm (mở bằng trình duyệt; nút: mái, trần, mặt tiền, kích thước)
B14: Drawings / Bản vẽ | C14: Plan R12-v8 (EN/RU) · Roof plan · S-01 Roof framing · S-02 Central dome · S-03 Chinar + skylight · S-04 Majolica column · S-05 Street portal (pishtaq) + sebil · S-06 Khiva arcade · S-07 Bar · S-08 Themed booth | D14: Mặt bằng R12-v8 · Mặt bằng mái · S-01 Khung mái · S-02 Mái vòm · S-03 Cây chinar + giếng trời · S-04 Cột majolica · S-05 Cổng pishtaq + sebil · S-06 Hàng vòm Khiva · S-07 Quầy bar · S-08 Ô ngồi chủ đề
B15: Prices / Giá | C15: VND, excluding VAT, including materials, labour, transport, installation, scaffolding and site cleaning. Give a separate line if something is excluded. | D15: VND, chưa VAT, bao gồm vật tư, nhân công, vận chuyển, lắp đặt, giàn giáo và vệ sinh. Ghi riêng nếu có phần không bao gồm.
B17: Example of a filled line / Ví dụ một dòng đã điền
B19: Code | C19: F01
B20: Item | C20: Carved armchair
B21: Unit | C21: pcs
B22: Qty | C22: 46
B23: Unit price VND | C23: 4800000
B24: Amount VND | C24: =C22*C23 -> 220800000
B25: Note | C25: Acacia wood, walnut stain; prototype 10 days
B26: Status | C26: Priced
B27: Yellow cells = your input (ô vàng = nhà thầu điền). Everything else is formula or our data.

Sheet Summary
B2: Summary / Tổng hợp (VND, excl. VAT unless stated)
B4: Code | C4: Section | D4: Hạng mục | E4: Amount VND | F4: Lines priced
B5: A | C5: Preliminaries, demolition, engineering | D5: Chuẩn bị, tháo dỡ, thiết kế kỹ thuật | E5: =BOQ!K2 -> 0 | F5: =COUNTIF(BOQ!M3:M6,"Priced")&" / 4" -> 0 / 4
B6: B | C6: Roof structure, skylight and dome | D6: Kết cấu mái, giếng trời và mái vòm | E6: =BOQ!K7 -> 0 | F6: =COUNTIF(BOQ!M8:M24,"Priced")&" / 17" -> 0 / 17
B7: C | C7: Floors, platform, ramp | D7: Sàn, bục, dốc | E7: =BOQ!K25 -> 0 | F7: =COUNTIF(BOQ!M26:M33,"Priced")&" / 8" -> 0 / 8
B8: D | C8: Street facade, signage, planting | D8: Mặt tiền đường, biển hiệu, cây xanh | E8: =BOQ!K34 -> 0 | F8: =COUNTIF(BOQ!M35:M46,"Priced")&" / 12" -> 0 / 12
B9: E | C9: Aivan (raised platform by the hall) | D9: Aivan (bục cao sát sảnh) | E9: =BOQ!K47 -> 0 | F9: =COUNTIF(BOQ!M48:M60,"Priced")&" / 13" -> 0 / 13
B10: F | C10: Dining terrace: furniture and features | D10: Khu ăn sân thượng: nội thất và điểm nhấn | E10: =BOQ!K61 -> 0 | F10: =COUNTIF(BOQ!M62:M72,"Priced")&" / 11" -> 0 / 11
B11: G | C11: Themed booths (8) | D11: Ô ngồi theo chủ đề (8) | E11: =BOQ!K73 -> 0 | F11: =COUNTIF(BOQ!M74:M77,"Priced")&" / 4" -> 0 / 4
B12: H | C12: Majlis tents and tapchan | D12: Lều majlis và giường tapchan | E12: =BOQ!K78 -> 0 | F12: =COUNTIF(BOQ!M79:M84,"Priced")&" / 6" -> 0 / 6
B13: I | C13: Bukhara rotunda, Khiva gate, corridor | D13: Nhà vòm Bukhara, cổng Khiva, hành lang | E13: =BOQ!K85 -> 0 | F13: =COUNTIF(BOQ!M86:M92,"Priced")&" / 7" -> 0 / 7
B14: J | C14: Bar | D14: Quầy bar | E14: =BOQ!K93 -> 0 | F14: =COUNTIF(BOQ!M94:M96,"Priced")&" / 3" -> 0 / 3
B15: K | C15: Mangal (grill) kitchen and sign | D15: Bếp nướng mangal và biển hiệu | E15: =BOQ!K97 -> 0 | F15: =COUNTIF(BOQ!M98:M105,"Priced")&" / 8" -> 0 / 8
B16: L | C16: Textiles and carpets | D16: Hàng dệt và thảm | E16: =BOQ!K106 -> 0 | F16: =COUNTIF(BOQ!M107:M110,"Priced")&" / 4" -> 0 / 4
B17: M | C17: Lighting | D17: Chiếu sáng | E17: =BOQ!K111 -> 0 | F17: =COUNTIF(BOQ!M112:M117,"Priced")&" / 6" -> 0 / 6
B18: N | C18: MEP, fire safety, AV | D18: Cơ điện, PCCC, âm thanh | E18: =BOQ!K118 -> 0 | F18: =COUNTIF(BOQ!M119:M123,"Priced")&" / 5" -> 0 / 5
C19: Subtotal works / Tổng cộng | E19: =SUM(E5:E18) -> 0
C20: Contingency / Dự phòng (%) | E20: =E19*F20 -> 0 | F20: 0.07
C21: Total before VAT / Tổng trước VAT | E21: =E19+E20 -> 0
C22: VAT (%) | E22: =E21*F22 -> 0 | F22: 0.08
C23: GRAND TOTAL / TỔNG CỘNG | E23: =E21+E22 -> 0
C25: Lines with status "Need info" | E25: =COUNTIF(BOQ!M2:M128,"Need info") -> 0
C26: Lines with status "Alternative" | E26: =COUNTIF(BOQ!M2:M128,"Alternative") -> 0
C27: Lines without status yet | E27: =COUNTA(BOQ!A2:A128)-15-COUNTA(BOQ!M2:M128) -> 112
C29: Contingency 7 % and VAT 8 % are editable defaults (yellow). VAT rate per current Vietnamese rules — adjust if your invoice uses 10 %.
B31: X | C31: ALTERNATIVES — price for comparison only (NOT added to the total) | D31: PHƯƠNG ÁN THAY THẾ — chỉ báo giá để so sánh (KHÔNG cộng vào tổng) | E31: =BOQ!K124 -> 0 | F31: =COUNTIF(BOQ!M125:M128,"Priced")&" / 4" -> 0 / 4

Sheet Design checks
A1: No | B1: Topic | C1: Point to check / Điểm cần kiểm tra | D1: Who | E1: Affects | F1: Contractor answer / Trả lời nhà thầu
A2: Q01 | B2: Structure | C2: Roof steel, dome and anchors must be designed and stamped by a licensed Vietnamese structural engineer (typhoon wind, uplift). Our sections (IPE 300, C200, SHS 150) are preliminary. | D2: Contractor / engineer | E2: Before pricing B
A3: Q02 | B3: Structure | C3: Existing building facade and slab: confirm they can take the C300 ledger and anchors; anchor pull-out tests on site. | D3: Engineer | E3: Before pricing B04
A4: Q03 | B4: Floor | C4: Polished natural marble is slippery when wet. Price marble-LOOK porcelain R11 (honed). Natural honed marble only as an alternative line. | D4: Owner decision | E4: Pricing C01
A5: Q04 | B5: Access | C5: The lift door opens onto the ramp slope. A level landing 1.5 × 1.5 m is required in front of the lift (included in C06). | D5: Owner / designer | E5: Confirmed
A6: Q05 | B6: Fire | C6: All textiles (drapes, swags, tents, flying / ceiling carpets, majlis) need fire-retardant treatment with certificates; keep fabrics ≥ 3 m from the mangal and tandoor. | D6: Contractor | E6: All L, I, H items
A7: Q06 | B7: Fire / gas | C7: Mangal kitchen: gas installation by a licensed contractor, leak detector, extinguishers, flue above the roof with spark arrestor. | D7: Contractor | E7: K items
A8: Q07 | B8: Climate | C8: Coastal humid / salty air: hardwood must be kiln-dried, sealed on all sides; brass with lacquer; steel C4 protection. Please state the wood species you price. | D8: Contractor | E8: All wood items
A9: Q08 | B9: Tree | C9: The chinar tree under the skylight is an existing tree. Arborist to confirm it can be kept, pruned and trained; protect roots during floor works. | D9: Arborist | E9: F04
A10: Q09 | B10: Water | C10: Hauz, aryk and sebil: waterproofing, recirculating pumps, RCD protection, easy cleaning access. | D10: Contractor | E10: F06, F07, D02
A11: Q10 | B11: Electrical | C11: All outdoor fittings IP65, 2700 K warm white, dimmable; display ≥ 1500 nits outdoor-rated. | D11: Contractor | E11: M, E08
A12: Q11 | B12: Permits | C12: Signage (SAMARKAND letters, display), roof structure and PCCC (fire) approvals from the local authorities. | D12: Owner / contractor | E12: D07, K08, N05
A13: Q12 | B13: Dome | C13: Dome is now LIGHTWEIGHT: FRP outer shell + GRG / FRP inner karbandi + 12-rib steel frame (≈ 1.5–2 t total instead of ≈ 5 t with GRC). Please price this as the main option and the heavy GRC version on the ALTERNATIVE lines (section X) for comparison. Engineer to confirm fixing against typhoon uplift. | D13: Contractor / engineer | E13: B12–B15, X01–X03
... A16: Q15 | B16: Scope | C16: NOT included: main kitchen equipment, tableware, uniforms, POS/IT, licences, loose decor collection for the rotunda unless priced separately. | D16: Owner | E16: —

Sheet BOQ
A1: Code Mã | B1: Item (EN) | C1: Hạng mục (VI) | D1: Specification / Quy cách | E1: Size / Kích thước | F1: Unit ĐV | G1: Qty SL | H1: Image / Hình | I1: Ref Bản vẽ | J1: Unit price VND Đơn giá | K1: Amount VND Thành tiền | L1: Contractor note Ghi chú nhà thầu | M1: Status Trạng thái
A2: A | B2: Preliminaries, demolition, engineering | C2: Chuẩn bị, tháo dỡ, thiết kế kỹ thuật | J2: Subtotal | K2: =SUM(K3:K6) -> 0
A3: A01 | B3: Site protection, hoarding, temporary power/water, cleaning | C3: Bảo vệ công trường, rào tạm, điện nước tạm, vệ sinh | D3: Whole terrace works area; restaurant hall stays closed to the works | E3: ≈ 450 m² | F3: lot | G3: 1 | I3: Plan | K3: =IF(J3="","",G3*J3)
A4: A02 | B4: Demolish existing pergola, louvres under balcony and old canopy; haul away | C4: Tháo dỡ giàn pergola, lam chắn nắng dưới ban công và mái che cũ; vận chuyển phế thải | D4: Keep the existing building facade, glazing and balcony slab intact | E4: — | F4: lot | G4: 1 | I4: Plan | K4: =IF(J4="","",G4*J4)
A5: A03 | B5: Remove old floor finish; levelling screed for new floor | C5: Đục bỏ lớp lát nền cũ; cán nền tạo phẳng | D5: Screed 40–50 mm, falls 1 % to drains; terrace level −0.450 | E5: 317 m² + kids 17 m² | F5: m² | G5: 334 | I5: Plan | K5: =IF(J5="","",G5*J5)
A6: A04 | B6: Structural design + permit drawings (roof steel, dome, anchors, footings) | C6: Thiết kế kết cấu + hồ sơ xin phép (khung thép mái, mái vòm, neo, móng) | D6: By a licensed Vietnamese structural engineer: typhoon wind (Da Nang), uplift, anchor pull-out tests, check of existing slab and facade for the ledger | E6: — | F6: lot | G6: 1 | I6: S-01, S-02 | K6: =IF(J6="","",G6*J6)
A7: B | B7: Roof structure, skylight and dome | C7: Kết cấu mái, giếng trời và mái vòm | J7: Subtotal | K7: =SUM(K8:K24) -> 0
A8: B01 | B8: Steel columns SHS 150×150×8 (S355), base plate 300×300×20, 4 chemical anchors M20 | C8: Cột thép hộp SHS 150×150×8 (S355), bản đế 300×300×20, 4 bu lông hóa chất M20 | D8: 11 columns, h ≈ 3.3 m; weight ≈ 1260 kg incl. plates | E8: 11 pcs | F8: kg | G8: 1260 | I8: S-01, S-04 | K8: =IF(J8="","",G8*J8)
A9: B02 | B9: Roof beams IPE 300 (S355) with end plates, cap plates, bolts M16 8.8 | C9: Dầm mái IPE 300 (S355) kèm bản mã, bu lông M16 cấp 8.8 | D9: 105.2 m on the column lines; bear on facade ledger and columns | E9: 105.2 m | F9: kg | G9: 4439 | I9: S-01 | K9: =IF(J9="","",G9*J9)
A10: B03 | B10: Purlins C200×75×20×2.5 galvanised @ 1000 with cleats | C10: Xà gồ C200×75×20×2.5 mạ kẽm @1000 kèm ke | D10: 381.8 m | E10: 381.8 m | F10: kg | G10: 2711 | I10: S-01 | K10: =IF(J10="","",G10*J10)
A11: B04 | B11: Facade ledger C300 on existing building, chemical anchors M16 @ 600 | C11: Thép C300 liên kết vào tường nhà hiện hữu, bu lông hóa chất M16 @600 | D11: 37.1 m along the hall facade; pull-out test before installation | E11: 37.1 m | F11: kg | G11: 1714 | I11: S-01 | K11: =IF(J11="","",G11*J11)
A12: B05 | B12: Corrosion protection for all roof steel (coastal C4) | C12: Chống ăn mòn cho toàn bộ thép mái (môi trường biển C4) | D12: Hot-dip galvanising + 1 finish coat, or epoxy zinc primer + epoxy + PU top coat (≥ 240 µm); colour bronze-black | E12: — | F12: kg | G12: 10124 | I12: S-01 | K12: =IF(J12="","",G12*J12)
A13: B06 | B13: Insulated sandwich roof panel PU 50 mm, underside wood-grain finish | C13: Tấm panel cách nhiệt PU 50 mm, mặt dưới vân gỗ | D13: Fall 5 % to the street; fixings with sealing washers; underside is the finished ceiling | E13: 413 m² | F13: m² | G13: 413 | I13: Roof plan | K13: =IF(J13="","",G13*J13)
A14: B07 | B14: Street box gutter 250 wide (galv. steel / stainless), outlets every 6 m | C14: Máng xối hộp rộng 250 (thép mạ kẽm / inox), thoát nước mỗi 6 m | D14: Overflow spouts; leaf guards | E14: 37.2 m | F14: m | G14: 37.2 | I14: Roof plan | K14: =IF(J14="","",G14*J14)
A15: B08 | B15: Downpipes inside / along columns + connection to site drainage | C15: Ống thoát nước mưa trong/dọc cột + đấu nối thoát nước | D15: uPVC Ø110, cleaning eyes | E15: 7 pcs | F15: pcs | G15: 7 | I15: Roof plan | K15: =IF(J15="","",G15*J15)
A16: B09 | B16: Roof-to-building flashing and sealing | C16: Diềm che, chống thấm tiếp giáp mái và nhà | D16: Folded flashing + PU sealant along the ledger | E16: 37.1 m | F16: m | G16: 37.1 | I16: Roof plan | K16: =IF(J16="","",G16*J16)
A17: B10 | B17: Skylight 3.0 × 3.0 over the chinar tree: laminated safety glass on steel upstand | C17: Giếng trời 3.0 × 3.0 trên cây chinar: kính an toàn dán trên khung thép | D17: Laminated glass 6+6 mm low-E, upstand 200 mm, sealed, falls to the roof; openable vent optional | E17: 9 m² | F17: m² | G17: 9 | I17: S-03 | K17: =IF(J17="","",G17*J17)
A18: B11 | B18: Carved walnut panjara (girih stars) under the skylight, hung on M8 rods | C18: Lưới gỗ chạm khắc (hoa văn sao girih) dưới giếng trời, treo bằng ty M8 | D18: Cell 215–360 mm, hardwood walnut stain, UV + humidity resistant finish | E18: 3.0 × 3.0 m | F18: m² | G18: 9 | I18: S-03 | K18: =IF(J18="","",G18*J18)
A19: B12 | B19: Central dome Ø5.6 — LIGHT steel frame: ring girder IPE 300 rolled (also carries roof beams), 12 rolled T80 ribs + 2 hoops L60, lantern ring CHS, drum studs SHS 60, top ring UPN 240 | C19: Mái vòm trung tâm Ø5.6 — khung thép NHẸ: dầm vòng IPE 300 uốn (đỡ cả dầm mái), 12 sườn T80 uốn + 2 vòng L60, vòng đỉnh CHS, cột trống SHS 60, vòng UPN 240 | D19: Lightweight FRP / GRG shells allow 12 ribs instead of 24 (≈ 900 kg instead of ≈ 1 400 kg). Final sections by the structural engineer. Galvanised, bolted splices | E19: Ø 5.6 m | F19: kg | G19: 900 | I19: S-02 | K19: =IF(J19="","",G19*J19)
... A24: B17 | B24: Ring gutter / flashing roof-to-dome | C24: Máng vòng / diềm tiếp giáp mái và vòm | D24: — | E24: 1 set | F24: lot | G24: 1 | I24: S-02 | K24: =IF(J24="","",G24*J24)
A25: C | B25: Floors, platform, ramp | C25: Sàn, bục, dốc | J25: Subtotal | K25: =SUM(K26:K33) -> 0
A26: C01 | B26: Terrace floor: marble-look porcelain 600×600 (honed, anti-slip R11) on a diagonal grid with mosaic chip bands | C26: Sàn sân: gạch porcelain vân đá 600×600 (mờ, chống trơn R11) lát chéo với dải mosaic | D26: Polished marble is NOT allowed outdoors (slippery when wet). Bands: 40 mm cobalt/terracotta chips as sample M10 | E26: 288 m² | F26: m² | G26: 288 | I26: Plan | K26: =IF(J26="","",G26*J26)
A27: C02 | B27: Zellige tile "carpets" 3.6 × 3.6 under the dome and around the chinar | C27: Thảm gạch zellige 3.6 × 3.6 dưới mái vòm và quanh cây chinar | D27: Glazed cut tiles 50–100 mm, star pattern as sample M11, border band | E27: 2 pcs = 25.9 m² | F27: m² | G27: 25.9 | I27: Plan | K27: =IF(J27="","",G27*J27)
A28: C03 | B28: Star mosaic medallion Ø2.6 around the hauz fountain | C28: Hoa văn mosaic hình sao Ø2.6 quanh hồ nước | D28: Glazed mosaic, cobalt / turquoise / white | E28: 3.6 m² | F28: m² | G28: 3.6 | I28: Plan | K28: =IF(J28="","",G28*J28)
A29: C04 | B29: Alley floor: star-tile runner with border (encaustic cement tile 200×200) | C29: Sàn lối đi: thảm gạch bông hình sao có viền (gạch bông 200×200) | D29: Pattern as sample M12 | E29: 15.8 m² | F29: m² | G29: 15.8 | I29: Plan | K29: =IF(J29="","",G29*J29)
A30: C05 | B30: Aivan platform ±0.000: steel frame + hardwood/WPC deck, 0.45 m above the terrace | C30: Bục aivan ±0.000: khung thép + sàn gỗ/gỗ nhựa, cao 0.45 m | D30: Deck oak colour; edge nosing; ventilation under the deck | E30: 49.3 m² | F30: m² | G30: 49.3 | I30: Plan | K30: =IF(J30="","",G30*J30)
A31: C06 | B31: Steps to the aivan + ramp 1:12 (1.3 m wide) + LEVEL landing 1.5 × 1.5 m at the lift door | C31: Bậc lên aivan + dốc 1:12 (rộng 1.3 m) + chiếu nghỉ PHẲNG 1.5 × 1.5 m trước cửa thang máy | D31: Handrails both sides on the ramp; anti-slip nosings | E31: 1 set | F31: lot | G31: 1 | I31: Plan | K31: =IF(J31="","",G31*J31)
A32: C07 | B32: Mangal kitchen floor: anti-slip slate / quarry tile + floor drain + grease trap | C32: Sàn bếp nướng: gạch đá chống trơn + thoát sàn + bẫy mỡ | D32: Falls to drain; washable | E32: 19.1 m² | F32: m² | G32: 19.1 | I32: Plan | K32: =IF(J32="","",G32*J32)
A33: C08 | B33: Kids corner: rubber safety surfacing 30 mm with pattern | C33: Khu trẻ em: sàn cao su an toàn 30 mm có họa tiết | D33: EN 1177 drop-height rated | E33: 17 m² | F33: m² | G33: 17 | I33: Plan | K33: =IF(J33="","",G33*J33)
A34: D | B34: Street facade, signage, planting | C34: Mặt tiền đường, biển hiệu, cây xanh | J34: Subtotal | K34: =SUM(K35:K46) -> 0
A35: D01 | B35: Pishtaq entrance portal: 2 pylons RC core + glazed brick (hazarbaf), kufic frames, majolica panels, 3-tier glazed GRC muqarnas; 4 steps from the sidewalk | C35: Cổng pishtaq: 2 trụ lõi BTCT + gạch men hazarbaf, khung kufic, tấm majolica, muqarnas GRC 3 tầng; 4 bậc từ vỉa hè | D35: Opening 2.5 m, clear height 2.32 m under the muqarnas (see S-05) | E35: 1 set | F35: lot | G35: 1 | I35: S-05 | K35: =IF(J35="","",G35*J35)
A36: D02 | B36: Sebil wall fountain (glazed brick, majolica tympanum, brass spout, stone basin, pump) | C36: Đài nước sebil gắn tường (gạch men, tympanum majolica, vòi đồng, chậu đá, bơm) | D36: Recirculating pump, RCD-protected | E36: 1 set | F36: lot | G36: 1 | I36: S-05 | K36: =IF(J36="","",G36*J36)
A37: D03 | B37: Majolica-clad columns along the street (GRC shell on the SHS column + majolica tiles, kufic bands) | C37: Cột ốp majolica dọc mặt đường (vỏ GRC bọc cột thép + gạch majolica, dải kufic) | D37: h 3.0 m, Ø ≈ 0.72 m with capital | E37: 7 pcs | F37: pcs | G37: 7 | I37: S-04 | K37: =IF(J37="","",G37*J37)
A38: D04 | B38: Street benches: cast concrete with majolica band + backrest | C38: Ghế băng mặt đường: bê tông đúc có dải majolica + tựa lưng | D38: 31 seats (not counted in the restaurant) | E38: 21.2 m | F38: m | G38: 21.2 | I38: Plan | K38: =IF(J38="","",G38*J38)
A39: D05 | B39: Street planter band: hazarbaf glazed brick cladding, waterproofing, drainage, soil, drip irrigation | C39: Bồn cây mặt đường: ốp gạch men hazarbaf, chống thấm, thoát nước, đất, tưới nhỏ giọt | D39: — | E39: 33.5 m | F39: m | G39: 33.5 | I39: Plan | K39: =IF(J39="","",G39*J39)
A40: D06 | B40: Street photo arch with niche + lighting | C40: Vòm chụp ảnh mặt đường có hốc + đèn | D40: — | E40: 1 pc | F40: pcs | G40: 1 | I40: Plan | K40: =IF(J40="","",G40*J40)
A41: D07 | B41: SAMARKAND channel letters, street side of the mangal wall (green LED face) + yellow subtitle | C41: Chữ nổi SAMARKAND mặt đường trên tường bếp nướng (mặt LED xanh) + dòng phụ màu vàng | D41: Letters h ≈ 0.46 m, length 2.4 m; subtitle "TAJIK AND UZBEK NATIONAL CUISINE"; IP65; signage permit | E41: 1 set | F41: lot | G41: 1 | I41: 3D | K41: =IF(J41="","",G41*J41)
A42: D08 | B42: Plumeria (frangipani) trees, trunk 8–10 cm | C42: Cây sứ (plumeria), thân 8–10 cm | D42: In the street planter | E42: 5 pcs | F42: pcs | G42: 5 | I42: Plan | K42: =IF(J42="","",G42*J42)
A43: D09 | B43: Areca palms (street planter 4 + kids corner 2) | C43: Cau kiểng (bồn đường 4 + khu trẻ em 2) | D43: h 1.8–2.2 m | E43: 6 pcs | F43: pcs | G43: 6 | I43: Plan | K43: =IF(J43="","",G43*J43)
A44: D10 | B44: Pomegranate trees (1 in the street bed + 2 in majolica urns by the alley) | C44: Cây lựu (1 bồn đường + 2 chậu majolica cạnh lối đi) | D44: h 1.8–2.2 m, with fruit | E44: 3 pcs | F44: pcs | G44: 3 | I44: Plan | K44: =IF(J44="","",G44*J44)
A45: D11 | B45: Majolica urn planters Ø0.57, h 0.6 (cobalt glaze, gold rim) | C45: Chậu gốm majolica Ø0.57 cao 0.6 (men xanh coban, viền vàng) | D45: Drain hole, saucer | E45: 2 pcs | F45: pcs | G45: 2 | I45: Plan | K45: =IF(J45="","",G45*J45)
A46: D12 | B46: Shrubs: bougainvillea 18, jasmine sambac 12, herbs 6, planter shrubs 7, aivan shrubs 3, banana 1 | C46: Cây bụi: hoa giấy 18, nhài 12, rau thơm 6, cây bụi bồn 7, cây bụi aivan 3, chuối 1 | D46: With supports / trellis for bougainvillea | E46: 47 pcs | F46: set | G46: 1 | I46: Plan | K46: =IF(J46="","",G46*J46)
A47: E | B47: Aivan (raised platform by the hall) | C47: Aivan (bục cao sát sảnh) | J47: Subtotal | K47: =SUM(K48:K60) -> 0
A48: E01 | B48: Khiva carved timber columns with 4-tier muqarnas capital and stone octagonal plinth | C48: Cột gỗ chạm Khiva với đầu cột muqarnas 4 tầng và chân đá bát giác | D48: Hardwood, h 2.78 m, Ø 0.30; plinth limestone 540 | E48: 10 pcs | F48: pcs | G48: 10 | I48: S-06 | K48: =IF(J48="","",G48*J48)
A49: E02 | B49: Arcade: carved pointed-arch heads + carved beam | C49: Hàng vòm: đầu vòm nhọn chạm khắc + dầm chạm | D49: Total length 13.2 m | E49: 13.2 m | F49: m | G49: 13.2 | I49: S-06 | K49: =IF(J49="","",G49*J49)
A50: E03 | B50: Arcade bays: jali panels (4) and majolica planter bays with shrubs (3) | C50: Khoang vòm: tấm jali (4) và khoang bồn cây majolica (3) | D50: Bay ≈ 0.94 × 1.96 m | E50: 7 bays | F50: pcs | G50: 7 | I50: S-06 | K50: =IF(J50="","",G50*J50)
A51: E04 | B51: Aivan edge rail with carved jali infill, h 1.0 m | C51: Lan can mép aivan với tấm jali chạm, cao 1.0 m | D51: — | E51: 21.3 m | F51: m | G51: 21.3 | I51: Plan / 3D | K51: =IF(J51="","",G51*J51)
A52: E05 | B52: Sedir booth benches 1.69 m, navy velvet seat + kilim cushions | C52: Ghế băng sedir 1.69 m, nệm nhung xanh navy + gối kilim | D52: Walnut plinth, channel-tufted back | E52: 8 pcs | F52: pcs | G52: 8 | I52: S-06 / 3D | K52: =IF(J52="","",G52*J52)
A53: E06 | B53: Carved tables 1.6 × 0.8 for the aivan booths | C53: Bàn chạm 1.6 × 0.8 cho các ô aivan | D53: Same family as F02 | E53: 4 pcs | F53: pcs | G53: 4 | I53: S-06 / 3D | K53: =IF(J53="","",G53*J53)
A54: E07 | B54: Carved jali screens between aivan booths, 1.9 × 1.2 m | C54: Vách jali chạm giữa các ô aivan, 1.9 × 1.2 m | D54: Walnut frame, pierced star jali, brass cap rail | E54: 5 pcs | F54: pcs | G54: 5 | I54: 3D viewer | K54: =IF(J54="","",G54*J54)
A55: E08 | B55: Aivan end screen with 65" outdoor display (landscape), facing the alley | C55: Vách đầu aivan có màn hình 65" ngoài trời (ngang), hướng ra lối đi | D55: Display ≥ 1500 nits, IP55, media player, power + data | E55: 1 pc | F55: pcs | G55: 1 | I55: 3D | K55: =IF(J55="","",G55*J55)
A56: E09 | B56: Wall carpets on the hall facade (framed, brass rod) | C56: Thảm treo tường trên mặt sảnh (khung, thanh đồng) | D56: 1.7 × 1.5 m each | E56: 4 pcs | F56: pcs | G56: 4 | I56: 3D viewer | K56: =IF(J56="","",G56*J56)
A57: E10 | B57: Zardevor embroidered friezes with tabs + tassels on brass rods | C57: Diềm thêu zardevor có tua và tua rua trên thanh đồng | D57: Lengths 1.08 / 2.29 / 2.6 m, h 0.55 m | E57: 3 pcs | F57: pcs | G57: 3 | I57: 3D | K57: =IF(J57="","",G57*J57)
A58: E11 | B58: Main hall door: carved walnut double door with jali panels, ring pulls, carved architrave, kufic crest | C58: Cửa chính sảnh: cửa đôi gỗ óc chó chạm, ô jali, tay nắm vòng, khung chạm, đỉnh chữ kufic | D58: 1.88 × 2.90 m overall | E58: 1 pc | F58: pcs | G58: 1 | I58: 3D | K58: =IF(J58="","",G58*J58)
A59: E12 | B59: Hall glass doors: bronze-framed glazed double doors with brass pulls + cobalt transom | C59: Cửa kính sảnh: cửa đôi khung đồng thau, tay nắm đồng + ô trên men coban | D59: 1.48 × 2.55 m | E59: 4 pcs | F59: pcs | G59: 4 | I59: 3D | K59: =IF(J59="","",G59*J59)
A60: E13 | B60: Lift portal trim (carved frame) — lift itself existing | C60: Khung trang trí cửa thang máy (khung chạm) — thang máy có sẵn | D60: 1.3 × 2.75 m | E60: 1 pc | F60: pcs | G60: 1 | I60: 3D | K60: =IF(J60="","",G60*J60)
A61: F | B61: Dining terrace: furniture and features | C61: Khu ăn sân thượng: nội thất và điểm nhấn | J61: Subtotal | K61: =SUM(K62:K72) -> 0
A62: F01 | B62: Carved armchair (Damascene): pierced jali back, stepped arched apron, kilim seat + back cushions, brass trim + feet | C62: Ghế bành chạm (kiểu Damascus): lưng jali xuyên, yếm vòm bậc, nệm ngồi + tựa kilim, viền và chân đồng | D62: 580 × 550, seat h 500, arms 660, back 970; hardwood walnut stain | E62: 46 pcs | F62: pcs | G62: 46 | I62: 3D viewer | K62: =IF(J62="","",G62*J62)
A63: F02 | B63: Carved table 4-seat 1400 × 800, top with mosaic / zellige inlay, arched apron | C63: Bàn chạm 4 chỗ 1400 × 800, mặt khảm mosaic / zellige, yếm vòm | D63: h 760; apron clearance 685 | E63: 8 pcs | F63: pcs | G63: 8 | I63: 3D viewer | K63: =IF(J63="","",G63*J63)
A64: F03 | B64: Carved table 2-seat 700 × 800 (same family) | C64: Bàn chạm 2 chỗ 700 × 800 (cùng mẫu) | D64: Modules can join into bigger tables | E64: 7 pcs | F64: pcs | G64: 7 | I64: 3D viewer | K64: =IF(J64="","",G64*J64)
A65: F04 | B65: Existing chinar (plane) tree under the skylight: arborist pruning/training, root zone protection | C65: Cây chinar (tiêu huyền) hiện hữu dưới giếng trời: cắt tỉa tạo tán, bảo vệ vùng rễ | D65: Crown kept 1.75–3.15 m above the terrace, clear of the roof | E65: 1 tree | F65: lot | G65: 1 | I65: S-03 | K65: =IF(J65="","",G65*J65)
A66: F05 | B66: Ring bench around the chinar: majolica ring + walnut cap + mulch bed + 3 uplights | C66: Ghế vòng quanh cây chinar: vòng majolica + mặt gỗ óc chó + lớp phủ + 3 đèn hắt | D66: Outer Ø 2.96 m, seat h 0.44 | E66: 1 pc | F66: pcs | G66: 1 | I66: S-03 | K66: =IF(J66="","",G66*J66)
A67: F06 | B67: Hauz fountain Ø1.2: majolica rim, stone coping, lotus jet, pump, 8 lights | C67: Hồ nước hauz Ø1.2: viền majolica, gờ đá, vòi hoa sen, bơm, 8 đèn | D67: Waterproofing, RCD, overflow | E67: 1 set | F67: lot | G67: 1 | I67: Plan | K67: =IF(J67="","",G67*J67)
A68: F07 | B68: Aryk water channel 0.3 × 4.2 m with majolica edges + stone bridge | C68: Mương nước aryk 0.3 × 4.2 m viền majolica + cầu đá | D68: Recirculation from the hauz | E68: 1 set | F68: lot | G68: 1 | I68: Plan | K68: =IF(J68="","",G68*J68)
A69: F08 | B69: Host stand: carved jali cabinet | C69: Quầy đón khách: tủ jali chạm | D69: 0.6 × 0.55 × 1.05 | E69: 1 pc | F69: pcs | G69: 1 | I69: Plan | K69: =IF(J69="","",G69*J69)
A70: F09 | B70: Staff station: 3 carved jali cabinets h 2.15 + 1 low cabinet + carved screen | C70: Trạm phục vụ: 3 tủ jali chạm cao 2.15 + 1 tủ thấp + vách chạm | D70: Shelving, POS, water, ice inside | E70: 1 set | F70: lot | G70: 1 | I70: Plan | K70: =IF(J70="","",G70*J70)
A71: F10 | B71: Kids corner: carved fence h 0.9 with gate, play elements, toy chests | C71: Khu trẻ em: hàng rào chạm cao 0.9 có cổng, đồ chơi, rương đồ chơi | D71: Rounded edges; safety glass check on the hall glazing | E71: 1 set | F71: lot | G71: 1 | I71: Plan | K71: =IF(J71="","",G71*J71)
A72: F11 | B72: Photo lounge "Ochag": portal drape, rug, LED fire bowl, 3 low tables, 12 poufs, jars, lanterns | C72: Góc chụp ảnh "Ochag": rèm cổng, thảm, bát lửa LED, 3 bàn thấp, 12 đôn, chum, đèn lồng | D72: Flame-retardant textiles | E72: 1 set | F72: lot | G72: 1 | I72: Plan | K72: =IF(J72="","",G72*J72)
A73: G | B73: Themed booths (8) | C73: Ô ngồi theo chủ đề (8) | J73: Subtotal | K73: =SUM(K74:K77) -> 0
A74: G01 | B74: Themed booth module 2.0 × 1.3 m: carved portal posts with majolica panels + stepped capitals, carved arch head, velvet cap with quilted suzani ceiling, curtains on brass rod, niche wall (plaster niches, epoch artwork), street parapet with majolica cap | C74: Ô ngồi theo chủ đề 2.0 × 1.3 m: trụ cổng chạm có tấm majolica + đầu cột bậc, đầu vòm chạm, trần nhung + trần thêu suzani, rèm trên thanh đồng, tường hốc (hốc thạch cao, tranh theo thời kỳ), lan can mặt đường có mũ majolica | D74: 8 themes: Sogd, Sasanid, Samanid, Khorezm, Timurid, Shahrisabz, Margilan, Pamir | E74: 8 pcs | F74: pcs | G74: 8 | I74: S-08 | K74: =IF(J74="","",G74*J74)
A75: G02 | B75: Booth banquettes 1.03 × 0.5, emerald velvet, channel-tufted back, kilim pillows | C75: Ghế băng ô ngồi 1.03 × 0.5, nhung xanh ngọc lục bảo, tựa chần sọc, gối kilim | D75: 2 per booth | E75: 16 pcs | F75: pcs | G75: 16 | I75: S-08 | K75: =IF(J75="","",G75*J75)
A76: G03 | B76: Booth table 0.9 × 0.8 with tile top | C76: Bàn ô ngồi 0.9 × 0.8 mặt gạch | D76: — | E76: 8 pcs | F76: pcs | G76: 8 | I76: S-08 | K76: =IF(J76="","",G76*J76)
A77: G04 | B77: Booth decor: theme object + 3 vases + framed artwork per booth | C77: Trang trí ô ngồi: vật phẩm chủ đề + 3 bình + tranh khung mỗi ô | D77: Artwork files supplied by the owner | E77: 8 sets | F77: set | G77: 8 | I77: S-08 | K77: =IF(J77="","",G77*J77)
A78: H | B78: Majlis tents and tapchan | C78: Lều majlis và giường tapchan | J78: Subtotal | K78: =SUM(K79:K84) -> 0
A79: H01 | B79: Majlis tent 2.6 × 2.75: steel/timber frame, striped FR canvas, scalloped valance, pitched roof | C79: Lều majlis 2.6 × 2.75: khung thép/gỗ, vải sọc chống cháy, diềm răng cưa, mái dốc | D79: Fabric fire certificate required | E79: 2 pcs | F79: pcs | G79: 2 | I79: Plan | K79: =IF(J79="","",G79*J79)
A80: H02 | B80: Majlis floor seating in red kilim: plinth h 0.14, seat mattress, back cushions (3 sides per tent) | C80: Ghế ngồi majlis bọc kilim đỏ: đế cao 0.14, nệm ngồi, gối tựa (3 phía mỗi lều) | D80: Lengths 1.7 / 1.7 / 2.7–2.8 m per tent | E80: 6 pcs | F80: pcs | G80: 6 | I80: Plan | K80: =IF(J80="","",G80*J80)
A81: H03 | B81: Octagonal Damascene table Ø0.66, h 0.45: mother-of-pearl inlay top, arched side panels | C81: Bàn bát giác Damascus Ø0.66 cao 0.45: mặt khảm xà cừ, hông vòm | D81: 2 per tent | E81: 4 pcs | F81: pcs | G81: 4 | I81: Plan | K81: =IF(J81="","",G81*J81)
A82: H04 | B82: Tapchan 2.0 × 2.2 (owner reference): tiled posts with turned finials, carved apron, plank deck h 0.45, turned-baluster rail on 3 sides | C82: Tapchan 2.0 × 2.2 (theo mẫu chủ đầu tư): trụ ốp gạch có chóp tiện, yếm chạm, sàn ván cao 0.45, lan can con tiện 3 phía | D82: Open side to the path | E82: 1 pc | F82: pcs | G82: 1 | I82: Plan | K82: =IF(J82="","",G82*J82)
A83: H05 | B83: Tapchan soft set: wine velvet kurpacha mattresses, palas rug, 6 adras/suzani pillows, 2 ikat bolsters | C83: Bộ nệm tapchan: nệm kurpacha nhung đỏ rượu, thảm palas, 6 gối adras/suzani, 2 gối ống ikat | D83: — | E83: 1 set | F83: set | G83: 1 | I83: Plan | K83: =IF(J83="","",G83*J83)
A84: H06 | B84: Tapchan low table 1.0 × 0.66, h 0.32, walnut with turned legs | C84: Bàn thấp tapchan 1.0 × 0.66 cao 0.32, gỗ óc chó chân tiện | D84: — | E84: 1 pc | F84: pcs | G84: 1 | I84: Plan | K84: =IF(J84="","",G84*J84)
A85: I | B85: Bukhara rotunda, Khiva gate, corridor | C85: Nhà vòm Bukhara, cổng Khiva, hành lang | J85: Subtotal | K85: =SUM(K86:K92) -> 0
A86: I01 | B86: Bukhara rotunda Ø2.1: podium, walnut lattice drum, 2 glass shelves, copper cap with gilt finial, 4 bronze posts, brass ring canopy, lighting | C86: Nhà vòm Bukhara Ø2.1: bục, trống lưới gỗ óc chó, 2 kệ kính, mũ đồng có chóp mạ vàng, 4 trụ đồng, vòng mái đồng thau, đèn | D86: Display of ceramics (collection listed in "Materials") | E86: 1 set | F86: lot | G86: 1 | I86: Plan | K86: =IF(J86="","",G86*J86)
A87: I02 | B87: Lit glass vitrines 0.3 × 0.3 on carved walnut bases | C87: Tủ kính có đèn 0.3 × 0.3 trên đế gỗ óc chó chạm | D87: — | E87: 4 pcs | F87: pcs | G87: 4 | I87: Plan | K87: =IF(J87="","",G87*J87)
A88: I03 | B88: Khiva gate 4.05 m: carved timber posts, beam, jali panel, brass capitals, 7 bells | C88: Cổng Khiva 4.05 m: trụ gỗ chạm, dầm, tấm jali, đầu cột đồng, 7 chuông | D88: — | E88: 1 set | F88: lot | G88: 1 | I88: Plan | K88: =IF(J88="","",G88*J88)
A89: I04 | B89: Draped corridor: 3 pointed arches, sagging velvet ceiling, pleated side drapes on brass rods (FR velvet) | C89: Hành lang rèm: 3 vòm nhọn, trần nhung võng, rèm xếp hai bên trên thanh đồng (nhung chống cháy) | D89: 2.8 × 2.5 m tunnel | E89: 1 set | F89: lot | G89: 1 | I89: Plan | K89: =IF(J89="","",G89*J89)
A90: I05 | B90: Crossed velvet swags (terracotta + wine) between the arches | C90: Rèm võng nhung bắt chéo (đất nung + đỏ rượu) giữa các vòm | D90: FR certified | E90: 2 sets | F90: set | G90: 2 | I90: 3D | K90: =IF(J90="","",G90*J90)
A91: I06 | B91: Wall niches with jars (4), terracotta amphorae (12), khum jars (2), LED pillar candles (6) | C91: Hốc tường có chum (4), bình gốm đất nung (12), chum lớn (2), nến LED trụ (6) | D91: Amphorae h 0.3–0.78 | E91: 1 set | F91: lot | G91: 1 | I91: 3D | K91: =IF(J91="","",G91*J91)
A92: I07 | B92: Rugs: Malayer runner 3.2 × 1.2 + 3 rugs 1.4 × 1.2 (layered) | C92: Thảm: thảm dài Malayer 3.2 × 1.2 + 3 thảm 1.4 × 1.2 (chồng lớp) | D92: Anti-slip underlay; outdoor-rated | E92: 4 pcs | F92: pcs | G92: 4 | I92: 3D | K92: =IF(J92="","",G92*J92)
A93: J | B93: Bar | C93: Quầy bar | J93: Subtotal | K93: =SUM(K94:K96) -> 0
A94: J01 | B94: Bar counter 5.7 m: terracotta fluted front, solid top, foot rail | C94: Quầy bar 5.7 m: mặt trước gạch đất nung sọc, mặt quầy đặc, thanh để chân | D94: h 1050 / overhang 300 | E94: 5.7 m | F94: m | G94: 5.7 | I94: S-07 | K94: =IF(J94="","",G94*J94)
A95: J02 | B95: Back bar wall with niches (stone + girih tiles), carved cornice with muqarnas corbels, shelves, wall carpet | C95: Tường sau quầy có hốc (đá + gạch girih), phào chạm có con sơn muqarnas, kệ, thảm treo | D95: 5.7 × 3.5 m | E95: 1 set | F95: lot | G95: 1 | I95: S-07 | K95: =IF(J95="","",G95*J95)
A96: J03 | B96: Bar stools, carved wood | C96: Ghế bar gỗ chạm | D96: seat h 720–760 | E96: 9 pcs | F96: pcs | G96: 9 | I96: S-07 | K96: =IF(J96="","",G96*J96)
A97: K | B97: Mangal (grill) kitchen and sign | C97: Bếp nướng mangal và biển hiệu | J97: Subtotal | K97: =SUM(K98:K105) -> 0
A98: K01 | B98: Copper-clad tandoor Ø0.9 in brick block | C98: Lò tandoor bọc đồng Ø0.9 trong khối gạch | D98: Clay tandoor (local or Uzbekistan) | E98: 1 pc | F98: pcs | G98: 1 | I98: Plan | K98: =IF(J98="","",G98*J98)
A99: K02 | B99: Mangal grill 2.0 m stainless + skewer rack | C99: Lò nướng mangal inox 2.0 m + giá xiên | D99: — | E99: 1 pc | F99: pcs | G99: 1 | I99: Plan | K99: =IF(J99="","",G99*J99)
A100: K03 | B100: Kazan Ø0.8 cast iron + high-pressure gas burner in brick block | C100: Chảo kazan gang Ø0.8 + bếp gas áp cao trong khối gạch | D100: — | E100: 1 set | F100: lot | G100: 1 | I100: Plan | K100: =IF(J100="","",G100*J100)
A101: K04 | B101: Exhaust hood 4.7 m stainless + fan + flue above the roof | C101: Chụp hút khói inox 4.7 m + quạt + ống khói vượt mái | D101: Flue 3.2 m above the hood; spark arrestor | E101: 1 set | F101: lot | G101: 1 | I101: Plan | K101: =IF(J101="","",G101*J101)
A102: K05 | B102: Pass 3.15 m with heat lamps + glass; prep table; sink + hand-wash; cold counter | C102: Quầy ra món 3.15 m có đèn giữ nóng + kính; bàn sơ chế; chậu rửa + rửa tay; bàn mát | D102: — | E102: 1 set | F102: lot | G102: 1 | I102: Plan | K102: =IF(J102="","",G102*J102)
A103: K06 | B103: Fire wall (masonry, bannai tile facing) + firewood display wall to the dining | C103: Tường chống cháy (xây, ốp gạch bannai) + tường trưng bày củi hướng khu ăn | D103: — | E103: 1 set | F103: lot | G103: 1 | I103: Plan | K103: =IF(J103="","",G103*J103)
A104: K07 | B104: Gas installation: piping, shut-off, leak detector | C104: Hệ thống gas: ống, van khóa, cảm biến rò rỉ | D104: Licensed gas contractor | E104: 1 set | F104: lot | G104: 1 | I104: Plan | K104: =IF(J104="","",G104*J104)
...

Sheet Materials
A1: Code | B1: Sample / Mẫu | C1: Material (EN) | D1: Vật liệu (VI) | E1: Where used / Vị trí | F1: Spec / Quy cách | G1: Contractor note / Ghi chú
A2: M01 | C2: Walnut-stain hardwood | D2: Gỗ cứng màu óc chó | E2: Chairs, tables, screens, columns, doors, cabinets | F2: Ash / acacia / teak, walnut stain, matt PU, humidity + UV resistant
A3: M02 | C3: Carved interlace panels | D3: Tấm chạm hoa văn đan | E3: Chair aprons, booth posts, apron bands | F3: CNC + hand finish
A4: M03 | C4: Pierced brass (lanterns) | D4: Đồng thau chạm lỗ (đèn lồng) | E4: Chandelier, pendants, lanterns, sconces | F4: Antique brass, star piercing, coloured glass jewels
A5: M04 | C5: Majolica tile — cobalt (Rishtan) | D5: Gạch majolica — xanh coban (Rishtan) | E5: Columns, booth posts, tapchan posts, planters | F5: Hand-painted glazed tile
A6: M05 | C6: Majolica tile — Isfahan | D6: Gạch majolica — Isfahan | E6: Pishtaq panels, sebil | F6: Glazed tile
A7: M06 | C7: Majolica band | D7: Dải gạch majolica | E7: Street benches, parapets | F7: Glazed tile band
A8: M07 | C8: Turquoise glazed brick (dome) | D8: Gạch men xanh ngọc (mái vòm) | E8: Dome exterior | F8: Ribbed pattern
A9: M08 | C9: Hazarbaf glazed brick | D9: Gạch men hazarbaf | E9: Pishtaq pylons, street planters | F9: Brick + glazed inserts
A10: M09 | C10: Kufic glazed brick | D10: Gạch men chữ kufic | E10: Dome drum, transoms, frames | F10: Glazed brick lettering
A11: M10 | C11: Marble-look porcelain + mosaic chip bands | D11: Porcelain vân đá + dải mosaic | E11: Terrace floor | F11: 600×600 honed, R11, diagonal grid
A12: M11 | C12: Zellige tile carpet | D12: Thảm gạch zellige | E12: Under the dome, around the chinar | F12: Glazed cut tile, star pattern
A13: M12 | C13: Encaustic star-tile runner | D13: Gạch bông hình sao | E13: Alley floor | F13: 200×200 cement tile
... A31: M30 | C31: Stone (coping, plinths) | D31: Đá (gờ, chân cột) | E31: Hauz coping, column plinths, benches | F31: Limestone, honed

Sheet References
B1: Owner reference photos / Ảnh tham khảo của chủ đầu tư — style and quality we expect
B18: Carved armchair (F01) | G18: Jali cabinets (F08, F09) | L18: Pierced brass lanterns (M02, M03)
B35: Lantern clusters (M01, M02) | G35: Pendant (M02) | L35: Sconce (M05)
B52: Floor grid with chip bands (C01) | G52: Zellige carpet (C02) | L52: Tile border (C04)
B69: Owner reference (R12-v8) | G69: Owner reference (R12-v8) | L69: Owner reference (R12-v8)
B86: Owner reference (R12-v8) | G86: Owner reference (R12-v8)
